{"meals":
    [{"idMeal":"53054",
        "strMeal":"Seri muka kuih",
        "strDrinkAlternate":null,
        "strCategory":"Dessert",
        "strArea":"Malaysian",
        "strInstructions":"Soak glutinous rice with water for at least 1 \u00bd hours prior to using. Drain.\r\nPrepare a 9-inch round or square cake pan and spray with cooking spray or line with plastic wrap.\r\nMix coconut milk, water, salt and the rice. Pour it into cake pan, topped with the pandan knots.\r\nSteam for 30 minutes.\r\nAfter 30 minutes, fluff up the rice and remove pandan knots. Then, using a greased spatula, flatten the steamed rice. Make sure there are no holes\/air bubbles and gaps in the rice, especially the sides.\r\nSteam for another 10 minutes.\r\n\r\nCombine pandan juice, coconut milk, all purpose flour, cornflour, and sugar. Mix well.\r\nAdd eggs and whisk well then strain into a medium sized metal bowl or pot.\r\nPlace pandan mixture over simmering water (double boiler or bain-marie)\r\nStir continuously and cook till custard starts to thicken. (15 minutes)\r\nPour pandan custard into glutinous rice layer, give it a little tap (for air bubbles) and continue to steam for 30 minutes.\r\nRemove kuih seri muka from the steamer and allow to cool completely before cutting into rectangles or diamond shapes.",
        "strMealThumb":"https:\/\/www.themealdb.com\/images\/media\/meals\/6ut2og1619790195.jpg",
        "strTags":null,
        "strYoutube":"https:\/\/www.youtube.com\/watch?v=_NJtCfqgaBo",
        "strIngredient1":"Rice",
        "strIngredient2":"Coconut Milk",
        "strIngredient3":"Water",
        "strIngredient4":"Salt",
        "strIngredient5":"Corn Flour",
        "strIngredient6":"Flour",
        "strIngredient7":"Eggs",
        "strIngredient8":"Coconut Cream",
        "strIngredient9":"Sugar",
        "strIngredient10":"",
        "strIngredient11":"",
        "strIngredient12":"",
        "strIngredient13":"",
        "strIngredient14":"",
        "strIngredient15":"",
        "strIngredient16":"",
        "strIngredient17":"",
        "strIngredient18":"",
        "strIngredient19":"",
        "strIngredient20":"",
        "strMeasure1":"400g",
        "strMeasure2":"150ml",
        "strMeasure3":"100ml",
        "strMeasure4":"1 tsp ",
        "strMeasure5":"5 tbs",
        "strMeasure6":"3 tbs",
        "strMeasure7":"3",
        "strMeasure8":"200ml",
        "strMeasure9":"140g",
        "strMeasure10":" ",
        "strMeasure11":" ",
        "strMeasure12":" ",
        "strMeasure13":" ",
        "strMeasure14":" ",
        "strMeasure15":" ",
        "strMeasure16":" ",
        "strMeasure17":" ",
        "strMeasure18":" ",
        "strMeasure19":" ",
        "strMeasure20":" ",
        "strSource":"https:\/\/makan.ch\/recipe\/kuih-seri-muka\/",
        "strImageSource":null,
        "strCreativeCommonsConfirmed":null,
        "dateModified":null}]}